httpexec/__init__.py
httpexec/__version__.py
httpexec/asgi.py
httpexec/etc/defaults.toml
httpexec-1.0.4.dist-info/LICENSE
httpexec-1.0.4.dist-info/METADATA
httpexec-1.0.4.dist-info/WHEEL
httpexec-1.0.4.dist-info/top_level.txt
httpexec-1.0.4.dist-info/RECORD
