Metadata-Version: 2.2
Name: httpexec
Version: 1.0.4
Summary: Execute CLI commands via a REST API.
Author-email: Michael Klatt <mdklatt@alumni.ou.edu>
License: The MIT License (MIT)
Project-URL: Homepage, https://github.com/mdklatt/httpexec
Project-URL: Repository, https://github.com/mdklatt/httpexec
Classifier: Development Status :: 5 - Production/Stable
Classifier: Environment :: Web Environment
Classifier: Intended Audience :: Developers
Classifier: Intended Audience :: System Administrators
Classifier: License :: OSI Approved :: MIT License
Classifier: Natural Language :: English
Classifier: Operating System :: OS Independent
Classifier: Programming Language :: Python
Classifier: Programming Language :: Python :: 3
Classifier: Programming Language :: Python :: 3.9
Classifier: Programming Language :: Python :: 3.10
Classifier: Programming Language :: Python :: 3.11
Classifier: Topic :: Internet :: WWW/HTTP :: Dynamic Content
Classifier: Topic :: Software Development :: User Interfaces
Requires-Python: >=3.9
License-File: LICENSE
Requires-Dist: quart<0.18,>=0.17.0
Requires-Dist: tomli<3,>=2.0.1; python_version < "3.11"
Requires-Dist: Werkzeug<2.4,>=2.3.8
Provides-Extra: dev
Requires-Dist: aiohttp<4,>=3.8.4; extra == "dev"
Requires-Dist: build<1,>=0.10.0; extra == "dev"
Requires-Dist: hypercorn<1,>=0.14.3; extra == "dev"
Requires-Dist: openapi-spec-validator<0.8.0,>=0.7.1; extra == "dev"
Requires-Dist: pytest<8,>=7.3.1; extra == "dev"
Requires-Dist: pytest-asyncio<1,>=0.21.0; extra == "dev"
Requires-Dist: sphinx<7,>=6.2.1; extra == "dev"
Requires-Dist: sphinx_rtd_theme<2,>=1.2.1; extra == "dev"
Requires-Dist: twine<7,>=6.1.0; extra == "dev"
